box_maker.py
cgm_cnn_rotations.py
generators.py
models.py
plot_maker.py
rotations.py
small_cgm_cnn.py
train_test.py
cgm_3d_cnn-0.0.2.dist-info/LICENSE.txt
cgm_3d_cnn-0.0.2.dist-info/METADATA
cgm_3d_cnn-0.0.2.dist-info/WHEEL
cgm_3d_cnn-0.0.2.dist-info/top_level.txt
cgm_3d_cnn-0.0.2.dist-info/RECORD
